generating/__init__.py
generating/generate.py
generating/html.py
generating/html_resource.py
parsing/__init__.py
parsing/excel.py
parsing/parse.py
parsing/spdx_license.py
test/__init__.py
test/test_parsing.py
tool/__init__.py
tool/oss_notice_tool.py
oss_notice_tool-0.0.2.dist-info/LICENSE
oss_notice_tool-0.0.2.dist-info/METADATA
oss_notice_tool-0.0.2.dist-info/WHEEL
oss_notice_tool-0.0.2.dist-info/entry_points.txt
oss_notice_tool-0.0.2.dist-info/top_level.txt
oss_notice_tool-0.0.2.dist-info/RECORD
