Metadata-Version: 2.1
Name: oss-notice-tool
Version: 0.0.2
Summary: generate open source software notice based on the SPDX document
Home-page: https://github.com/sktelecom/oss-notice-tool
Author: Haksung Jang
Author-email: hakssung@gmail.com
Classifier: Programming Language :: Python :: 3
Classifier: License :: OSI Approved :: Apache Software License
Classifier: Operating System :: OS Independent
Requires-Python: >=3.6
License-File: LICENSE
